{"cameraMode":{"drawMode":0,"name":"Shaded","section":"Shading Mode"},"sceneLighting":true,"audioPlay":false,"sceneViewState":{"showFog":true,"showMaterialUpdate":false,"showSkybox":true,"showFlares":true,"showImageEffects":true,"showParticleSystems":true},"in2DMode":false,"pivot":{"x":128.25247192382813,"y":-52.88489532470703,"z":81.76995849609375},"rotation":{"x":0.16376611590385438,"y":0.49291279911994936,"z":-0.09504985064268112,"w":0.8492311835289002},"size":313.1037292480469,"orthographic":false}